{"Count": 15, "Message": "Response returned successfully", "SearchCriteria": "Make:Porsche", "Results": [{"Make_ID": 584, "Make_Name": "Porsche", "Model_ID": 7832, "Model_Name": "911"}, {"Make_ID": 584, "Make_Name": "Porsche", "Model_ID": 7847, "Model_Name": "Boxster"}, {"Make_ID": 584, "Make_Name": "Porsche", "Model_ID": 7895, "Model_Name": "Cayenne"}, {"Make_ID": 584, "Make_Name": "Porsche", "Model_ID": 7900, "Model_Name": "Cayman"}, {"Make_ID": 584, "Make_Name": "Porsche", "Model_ID": 7994, "Model_Name": "Panamera"}, {"Make_ID": 584, "Make_Name": "Porsche", "Model_ID": 8022, "Model_Name": "918"}, {"Make_ID": 584, "Make_Name": "Porsche", "Model_ID": 8031, "Model_Name": "Macan"}, {"Make_ID": 584, "Make_Name": "Porsche", "Model_ID": 13846, "Model_Name": "944"}, {"Make_ID": 584, "Make_Name": "Porsche", "Model_ID": 13847, "Model_Name": "928"}, {"Make_ID": 584, "Make_Name": "Porsche", "Model_ID": 13848, "Model_Name": "924"}, {"Make_ID": 584, "Make_Name": "Porsche", "Model_ID": 14080, "Model_Name": "968"}, {"Make_ID": 584, "Make_Name": "Porsche", "Model_ID": 28090, "Model_Name": "Taycan"}, {"Make_ID": 584, "Make_Name": "Porsche", "Model_ID": 31222, "Model_Name": "718 Boxster"}, {"Make_ID": 584, "Make_Name": "Porsche", "Model_ID": 31223, "Model_Name": "718 Spyder"}, {"Make_ID": 584, "Make_Name": "Porsche", "Model_ID": 31224, "Model_Name": "718 Cayman"}]}